src/__init__.py
src/main.py
src/config/__init__.py
src/config/main.py
src/interfaces/__init__.py
src/interfaces/account.py
src/interfaces/ads.py
src/interfaces/attachments.py
src/interfaces/groups.py
src/interfaces/main.py
src/interfaces/photo.py
src/interfaces/video.py
src/interfaces/wall.py
src/service/__init__.py
src/service/main.py
vk_connector-1.0.0.dist-info/LICENSE
vk_connector-1.0.0.dist-info/METADATA
vk_connector-1.0.0.dist-info/WHEEL
vk_connector-1.0.0.dist-info/top_level.txt
vk_connector-1.0.0.dist-info/RECORD
